workspaces_sdk/__init__.py
workspaces_sdk/addon.py
workspaces_sdk/analytics.py
workspaces_sdk/billing.py
workspaces_sdk/client.py
workspaces_sdk/config.py
workspaces_sdk/configuration.py
workspaces_sdk/credit.py
workspaces_sdk/data_export.py
workspaces_sdk/newsletter.py
workspaces_sdk/notification.py
workspaces_sdk/organization.py
workspaces_sdk/payment.py
workspaces_sdk/plan.py
workspaces_sdk/project.py
workspaces_sdk/quota.py
workspaces_sdk/rbac.py
workspaces_sdk/settings.py
workspaces_sdk/store.py
workspaces_sdk/team.py
workspaces_sdk/usage.py
workspaces_sdk/workspace.py
workspaces_sdk-1.0.0.dist-info/licenses/LICENSE
workspaces_sdk-1.0.0.dist-info/METADATA
workspaces_sdk-1.0.0.dist-info/WHEEL
workspaces_sdk-1.0.0.dist-info/top_level.txt
workspaces_sdk-1.0.0.dist-info/RECORD
