Metadata-Version: 2.4
Name: workspaces-sdk
Version: 1.0.0
Summary: Python SDK for Workspaces API with Enhanced Actor-based RBAC
Author-email: Algoshred <support@algoshred.com>
Project-URL: Homepage, https://github.com/Algoshred/workspaces-sdk-python
Project-URL: Repository, https://github.com/Algoshred/workspaces-sdk-python
Classifier: Development Status :: 4 - Beta
Classifier: Intended Audience :: Developers
Classifier: License :: OSI Approved :: MIT License
Classifier: Programming Language :: Python :: 3
Classifier: Programming Language :: Python :: 3.8
Classifier: Programming Language :: Python :: 3.9
Classifier: Programming Language :: Python :: 3.10
Classifier: Programming Language :: Python :: 3.11
License-File: LICENSE
Requires-Dist: gql[requests]>=3.4.0
Requires-Dist: requests>=2.25.0
Requires-Dist: typing-extensions>=4.0.0
Requires-Dist: python-dotenv>=1.0.0
Provides-Extra: dev
Requires-Dist: pytest>=7.0.0; extra == "dev"
Requires-Dist: pytest-asyncio>=0.21.0; extra == "dev"
Requires-Dist: black>=22.0.0; extra == "dev"
Requires-Dist: flake8>=4.0.0; extra == "dev"
Requires-Dist: mypy>=0.991; extra == "dev"
Dynamic: license-file
